AsyncLine/__init__.py
AsyncLine/auth.py
AsyncLine/buddy.py
AsyncLine/call.py
AsyncLine/channel.py
AsyncLine/config.py
AsyncLine/connections.py
AsyncLine/database.py
AsyncLine/filters.py
AsyncLine/handler.py
AsyncLine/http_client.py
AsyncLine/liff.py
AsyncLine/log.py
AsyncLine/main.py
AsyncLine/models.py
AsyncLine/poll.py
AsyncLine/proto.py
AsyncLine/shop.py
AsyncLine/talk.py
AsyncLine/timeline.py
AsyncLine/lib/__init__.py
AsyncLine/lib/Gen/__init__.py
AsyncLine/lib/Gen/constants.py
AsyncLine/lib/Gen/f_LineService.py
AsyncLine/lib/Gen/ttypes.py
AsyncLine/lib/Gen/liff/__init__.py
AsyncLine/lib/Gen/liff/constants.py
AsyncLine/lib/Gen/liff/f_LiffService.py
AsyncLine/lib/Gen/liff/ttypes.py
AsyncLine-1.5.9.5.dist-info/LICENSE
AsyncLine-1.5.9.5.dist-info/METADATA
AsyncLine-1.5.9.5.dist-info/WHEEL
AsyncLine-1.5.9.5.dist-info/top_level.txt
AsyncLine-1.5.9.5.dist-info/RECORD
