Metadata-Version: 2.1
Name: AsyncLine
Version: 1.5.9.5
Summary: LINE Unofficial Python Library with Asyncio support and C++ Binding
Home-page: https://github.com/dyseo/AsyncLine
Author: Anysz, Doodspav, Dyseo
Author-email: katro.coplax@gmail.com
License: MIT
Download-URL: https://github.com/dyseo/AsyncLine/releases/latest
Platform: UNKNOWN
Classifier: Development Status :: 4 - Beta
Classifier: Programming Language :: Python
Classifier: Natural Language :: English
Classifier: License :: OSI Approved :: MIT License
Classifier: Programming Language :: Python :: 3.6
Classifier: Programming Language :: Python :: 3.7
Classifier: Topic :: Internet
Requires-Dist: aiohttp
Requires-Dist: aiostomp
Requires-Dist: async-timeout
Requires-Dist: asyncio-nats-client
Requires-Dist: frugal
Requires-Dist: pymongo
Requires-Dist: requests
Requires-Dist: rsa
Provides-Extra: uvloop
Requires-Dist: uvloop (==0.13.0) ; extra == 'uvloop'
